django_static_engine-0.1.8.dist-info/licenses/LICENSE
static_engine/__init__.py
static_engine/apps.py
static_engine/urls.py
static_engine/utils.py
static_engine/views.py
static_engine/templates/__directory__.html
django_static_engine-0.1.8.dist-info/METADATA
django_static_engine-0.1.8.dist-info/WHEEL
django_static_engine-0.1.8.dist-info/top_level.txt
django_static_engine-0.1.8.dist-info/RECORD
